odoo/addons/stock_vertical_lift_packaging_level/README.rst
odoo/addons/stock_vertical_lift_packaging_level/__init__.py
odoo/addons/stock_vertical_lift_packaging_level/__manifest__.py
odoo/addons/stock_vertical_lift_packaging_level/i18n/it.po
odoo/addons/stock_vertical_lift_packaging_level/i18n/stock_vertical_lift_packaging_level.pot
odoo/addons/stock_vertical_lift_packaging_level/i18n/stock_vertical_lift_packaging_type.pot
odoo/addons/stock_vertical_lift_packaging_level/readme/CONTRIBUTORS.md
odoo/addons/stock_vertical_lift_packaging_level/readme/DESCRIPTION.md
odoo/addons/stock_vertical_lift_packaging_level/static/description/icon.png
odoo/addons/stock_vertical_lift_packaging_level/static/description/index.html
odoo/addons/stock_vertical_lift_packaging_level/views/shuttle_screen_templates.xml
odoo_addon_stock_vertical_lift_packaging_level-18.0.1.0.0.2.dist-info/METADATA
odoo_addon_stock_vertical_lift_packaging_level-18.0.1.0.0.2.dist-info/WHEEL
odoo_addon_stock_vertical_lift_packaging_level-18.0.1.0.0.2.dist-info/top_level.txt
odoo_addon_stock_vertical_lift_packaging_level-18.0.1.0.0.2.dist-info/RECORD
